AUTHORS.rst
LICENSE
MANIFEST.in
README.rst
pyproject.toml
requirements.txt
setup.py
tnltk/__init__.py
tnltk/normalizer/__init__.py
tnltk/normalizer/_normalizer_builtin.py
tnltk/normalizer/deasciifier.py
tnltk/normalizer/normalizer.py
tnltk/sentence_splitter/__init__.py
tnltk/sentence_splitter/sentence_splitter.py
ttkk_deneme.egg-info/PKG-INFO
ttkk_deneme.egg-info/SOURCES.txt
ttkk_deneme.egg-info/dependency_links.txt
ttkk_deneme.egg-info/top_level.txt