Metadata-Version: 2.1
Name: ttkk-deneme
Version: 0.1.2
Summary: TNLTK - Turkish Natural Language Toolkit developed by TNLTK Development Team.
Home-page: https://github.com/tnltk/tnltk
Author: Tarik Kaan Koc
License: Apache License, Version 2.0
Keywords: machine-learning,deep-learning,ml,nlp,turkish-nlp
Platform: UNKNOWN
Classifier: Development Status :: 2 - Pre-Alpha
Classifier: Intended Audience :: Developers
Classifier: Intended Audience :: Education
Classifier: Intended Audience :: Science/Research
Classifier: Topic :: Scientific/Engineering
Classifier: Topic :: Scientific/Engineering :: Artificial Intelligence
Classifier: Topic :: Scientific/Engineering :: Information Analysis
Classifier: Topic :: Text Processing
Classifier: Topic :: Software Development
Classifier: Topic :: Software Development :: Libraries
Classifier: Programming Language :: Python
Classifier: Programming Language :: Python :: 3.7
Classifier: Programming Language :: Python :: 3.8
Classifier: Programming Language :: Python :: 3.9
Requires-Python: >=3.7
